[
  {
    "uuid": "ccbcde15-1bb4-40e5-9352-d940387bddf9",
    "name": "SweetPee823",
    "level": 4,
    "bypassesPlayerLimit": false
  },
  {
    "uuid": "1268bdff-7a6c-4438-a3fa-7df24164ee4a",
    "name": "John825",
    "level": 4,
    "bypassesPlayerLimit": false
  },
  {
    "uuid": "65ee5d9b-44e7-4770-8c25-5272c8b781be",
    "name": "pieman63",
    "level": 4,
    "bypassesPlayerLimit": false
  },
  {
    "uuid": "a763c028-7345-46f0-ad74-139e15d315d0",
    "name": "tim127",
    "level": 4,
    "bypassesPlayerLimit": false
  }
]